graphmemory/__init__.py
graphmemory/database.py
graphmemory/models.py
graphmemory-0.2.1.dist-info/METADATA
graphmemory-0.2.1.dist-info/WHEEL
graphmemory-0.2.1.dist-info/top_level.txt
graphmemory-0.2.1.dist-info/RECORD
